idf_analysis/__init__.py
idf_analysis/__main__.py
idf_analysis/_console_script.py
idf_analysis/arg_parser.py
idf_analysis/definitions.py
idf_analysis/extrem_value_series.py
idf_analysis/extreme_value_analysis_2025.py
idf_analysis/heavy_rainfall_index.py
idf_analysis/idf_backend_2012.py
idf_analysis/idf_backend_2025.py
idf_analysis/idf_backend_abstract.py
idf_analysis/idf_class.py
idf_analysis/in_out.py
idf_analysis/intensity_evaluation.py
idf_analysis/little_helpers.py
idf_analysis/parameter_formulas.py
idf_analysis/plot_helpers.py
idf_analysis/sww_utils.py
idf_analysis/synthetic_rainseries.py
idf_analysis/approaches/ATV-A_121.yaml
idf_analysis/approaches/KOSTRA.yaml
idf_analysis/approaches/convective_vs_advective.yaml
idf_analysis-0.4.1.dist-info/licenses/LICENSE
idf_analysis-0.4.1.dist-info/METADATA
idf_analysis-0.4.1.dist-info/WHEEL
idf_analysis-0.4.1.dist-info/entry_points.txt
idf_analysis-0.4.1.dist-info/top_level.txt
idf_analysis-0.4.1.dist-info/RECORD
