Metadata-Version: 2.4
Name: idf-analysis
Version: 0.4.1
Summary: heavy rainfall intensity as a function of duration and return period acc. to DWA-A 531 (2012)
Author-email: Markus Pichler <markus.pichler@tugraz.at>
License-Expression: MIT
Project-URL: Documentation, https://markuspic.github.io/intensity_duration_frequency_analysis/
Project-URL: Changelog, https://github.com/MarkusPic/intensity_duration_frequency_analysis/blob/main/CHANGELOG.md
Project-URL: homepage, https://github.com/MarkusPic/intensity_duration_frequency_analysis
Project-URL: funding, https://www.buymeacoffee.com/MarkusP
Keywords: duration,analysis,rainfall,dwd,idf,measurement-data,precipitation,kostra,dwa,heavy-rain,intensity-duration-frequency,design-rainfall,duration-steps,return-period,dwa-a-531
Classifier: Programming Language :: Python :: 3
Classifier: Operating System :: OS Independent
Classifier: Development Status :: 4 - Beta
Classifier: Natural Language :: English
Classifier: Topic :: Scientific/Engineering
Classifier: Topic :: Scientific/Engineering :: Hydrology
Classifier: Intended Audience :: Science/Research
Requires-Python: >=3.7
License-File: LICENSE
Requires-Dist: pandas
Requires-Dist: tqdm
Requires-Dist: matplotlib
Requires-Dist: scipy
Requires-Dist: PyYAML>=5
Requires-Dist: sympy
Provides-Extra: docs
Requires-Dist: sphinx; extra == "docs"
Requires-Dist: nbsphinx; extra == "docs"
Requires-Dist: recommonmark; extra == "docs"
Requires-Dist: myst-parser; extra == "docs"
Requires-Dist: pydata_sphinx_theme; extra == "docs"
Requires-Dist: ipython==8.5.0; extra == "docs"
Requires-Dist: sphinx-codeautolink; extra == "docs"
Provides-Extra: testing
Requires-Dist: pytest; extra == "testing"
Requires-Dist: pytest-cov; extra == "testing"
Requires-Dist: pyarrow; extra == "testing"
Dynamic: license-file
